spcancestry/__init__.py
spcancestry/spcancestry.py
spcancestry-0.1.0.dist-info/LICENSE
spcancestry-0.1.0.dist-info/METADATA
spcancestry-0.1.0.dist-info/WHEEL
spcancestry-0.1.0.dist-info/top_level.txt
spcancestry-0.1.0.dist-info/RECORD
