Metadata-Version: 2.1
Name: spcancestry
Version: 0.1.0
Summary: SPCAncestry: A Python package for inferring population ancestry.
Home-page: https://github.com/LindoNkambule/spcancestry
Author: Lindokuhle Nkambule
Author-email: lnkambule@hsph.harvard.edu
License: MIT
Project-URL: GitHub, https://github.com/LindoNkambule/spcancestry
Classifier: Development Status :: 4 - Beta
Classifier: Environment :: Console
Classifier: Intended Audience :: Science/Research
Classifier: License :: OSI Approved :: MIT License
Classifier: Programming Language :: Python :: 3
Classifier: Programming Language :: Python :: 3.2
Classifier: Programming Language :: Python :: 3.3
Classifier: Programming Language :: Python :: 3.4
Classifier: Programming Language :: Python :: 3.5
Classifier: Programming Language :: Python :: 3.6
Classifier: Programming Language :: Python :: 3.7
Classifier: Programming Language :: Python :: 3.8
Classifier: Topic :: Scientific/Engineering :: Bio-Informatics
Classifier: Operating System :: POSIX
Classifier: Operating System :: Unix
Classifier: Operating System :: MacOS
License-File: LICENSE
Requires-Dist: hail
Requires-Dist: pandas
Requires-Dist: sklearn
